<?xml version="1.0" encoding="UTF-8" standalone="yes"?>
<items>
  <description>
    <item>10月5日（じゅうがついつか）はグレゴリオ暦で年始から278日目（閏年では279日目）にあたり、年末まであと87日ある。</item>
  </description>
  <events>
    <item>610年 - ヘラクレイオスが東ローマ皇帝に即位。</item>
    <item>869年 - 第4コンスタンティノポリス公会議が開会。</item>
    <item>1665年 - 創立。</item>
    <item>1710年 - ポートロワイヤルの戦いはじまる。</item>
    <item>1789年 - フランス革命: ヴェルサイユ行進。パリの主婦らがヴェルサイユ宮殿まで行進し、国王ルイ16世をパリに連行。</item>
    <item>1793年 - フランス革命: キリスト教がフランスの国教としての地位を失う。</item>
    <item>1795年（フランス革命暦4年ヴァンデミエール13日） - フランス革命: ヴァンデミエールの反乱</item>
    <item>1813年 - 米英戦争: テムズの戦いで米軍勝利。</item>
    <item>1864年 - インドのコルカタがサイクロンで破壊される。死者6万人。</item>
    <item>1894年 - 庚寅新誌社が日本初の月刊時刻表『汽車汽船旅行案内』を出版。</item>
    <item>1895年 - ロンドンの北で最初の個人タイムトライアル自転車レース（50マイル）が開催。</item>
    <item>1908年 - オーストリア＝ハンガリー帝国がボスニア・ヘルツェゴビナを併合。</item>
    <item>1910年 - 1910年10月5日革命。ポルトガルで王制を廃止し共和制に移行。</item>
    <item>1915年 - 第一次世界大戦: ブルガリアが中央同盟国側として参戦。</item>
    <item>1921年 - 国際ペンクラブ発足。</item>
    <item>1921年 - 米メジャーリーグのワールドシリーズが初めてラジオ中継される。</item>
    <item>1926年 - 新交響楽団（NHK交響楽団の前身）が結成される。</item>
    <item>1930年 - イギリスの飛行船R101がインドに向けて飛行中パリ近郊で山腹に衝突。</item>
    <item>1931年 - アメリカの長距離機ミス・ビードル号が初の太平洋無着陸横断飛行に成功。</item>
    <item>1937年 - 第二次世界大戦: フランクリン・ルーズヴェルト米大統領が「日独伊3国は『隔離』されなければならない」と演説（隔離演説）。</item>
    <item>1943年 - 第二次世界大戦: 関釜連絡船・崑崙丸が米艦の雷撃を受けて沈没。衆議院議員2人を含む544人が死亡</item>
    <item>1945年 - 東久邇宮内閣が、前日のGHQによる「民権自由に関する指令」を受け入れられないとして総辞職。</item>
    <item>1947年 - ハリー・S・トルーマン米大統領が初のホワイトハウスからのテレビ演説。</item>
    <item>1947年 - コミンフォルム結成。</item>
    <item>1953年 - アール・ウォーレンが第14代アメリカ合衆国最高裁判所長官に指名される。</item>
    <item>1962年 - 映画007シリーズ第1作『007 ドクター・ノオ』がイギリスで公開。</item>
    <item>1962年 - ビートルズのファースト・シングル『ラヴ・ミー・ドゥ/P.S.アイ・ラヴ・ユー』がイギリスでリリース。</item>
    <item>1964年 - 国鉄と日本急行バスにより名神ハイウェイバスが開業。日本初の高速バス。</item>
    <item>1966年 - 米デトロイト郊外のエンリコ・フェルミ炉で史上初の炉心溶融事故がおこる。</item>
    <item>1969年 - イギリス・BBCのコメディ番組『空飛ぶモンティ・パイソン』が放送開始。</item>
    <item>1969年 - テレビアニメ『サザエさん』（フジテレビ系）放送開始。</item>
    <item>1970年 - 公共放送サービス開局。</item>
    <item>1973年 - ミュンヘンで欧州特許付与に関する条約が締結。</item>
    <item>1980年 - 山口百恵の引退コンサートが日本武道館で行なわれる。</item>
    <item>1981年 - ラウル・ワレンバーグにアメリカ名誉市民の称号が贈られる。</item>
    <item>1983年 - レフ・ヴァウェンサのノーベル平和賞受賞が決定。</item>
    <item>1983年 - 敗戦後アメリカ軍に接収されたままだった赤坂の山王ホテルが所有者に返還。</item>
    <item>1988年 - チリのアウグスト・ピノチェト大統領が国民信任投票で敗北。15年間の軍事独裁が終焉。</item>
    <item>1989年 - ダライ・ラマ14世のノーベル平和賞受賞が決定。</item>
    <item>1989年 - 京阪鴨東線（三条 - 出町柳間2.3km）が開業。</item>
    <item>1991年 - TBS系の期首期末特番『オールスター感謝祭』が放送開始。</item>
    <item>1993年 - 大阪市交通局南港ポートタウン線（ニュートラム）の住之江公園駅構内で車両暴走事故。乗客215人が負傷。</item>
    <item>1998年 - NHKのアニメ番組『おじゃる丸』が放送開始。</item>
    <item>1999年 - 小渕再改造内閣が発足。</item>
    <item>1999年 - SPEEDが解散を発表。</item>
    <item>2000年 - ロト6第1回抽選。</item>
    <item>2003年 - アフマド・カディロフがチェチェン共和国の大統領に選ばれる。</item>
    <item>2010年 - マット・マートン（阪神タイガース）がイチローの持つ日本プロ野球シーズン最多安打記録（210本）を更新。</item>
  </events>
  <birthday>
    <item>1713年 - ドニ・ディドロ、哲学者（+ 1784年）</item>
    <item>1751年（寛延4年8月16日） - 徳川治保、常陸国水戸藩の第6代藩主（+ 1805年）</item>
    <item>1799年（寛政11年9月7日） - 箕作阮甫、蘭学者（+ 1863年）</item>
    <item>1812年 - チェスター・A・アーサー、第20代・21代アメリカ合衆国大統領（+ 1886年）</item>
    <item>1813年 - エルンスト・ハーベルビアー、作曲家、ピアニスト（+ 1869年）</item>
    <item>1836年（天保7年8月25日） - 榎本武揚、政治家（+ 1908年）</item>
    <item>1840年 - ヨーハン2世、リヒテンシュタイン公（+ 1929年）</item>
    <item>1856年 - ユーリ・ショカルスキー、地理学者、海洋学者（+ 1940年）</item>
    <item>1882年 - ロバート・ゴダード、ロケット工学者（+ 1945年）</item>
    <item>1886年 - 徳川義親、尾張徳川家第19代当主（+ 1976年）</item>
    <item>1891年 - 大濱信泉、法学者、教育者（+ 1976年）</item>
    <item>1892年 - 渋沢秀雄、実業家、随筆家（+ 1984年）</item>
    <item>1895年 - スベア・ノーレン、フィギュアスケート選手（+ 1985年）</item>
    <item>1898年 - 政岡憲三、アニメーション監督（+ 1988年）</item>
    <item>1900年 - 平澤興、医学者、京都大学第16代総長（+ 1989年）</item>
    <item>1900年 - 中山義秀、小説家（+ 1969年）</item>
    <item>1902年 - 浦辺粂子、女優（+ 1989年）</item>
    <item>1903年 - 藤井松太郎、第7代日本国有鉄道総裁（+ 1988年）</item>
    <item>1903年 - 北畠八穂、詩人、児童文学作家（+ 1982年）</item>
    <item>1908年 - ディック・ミネ、歌手（+ 1991年）</item>
    <item>1909年 - 増本勇、元調教師（+ 1986年）</item>
    <item>1915年 - 南美江、女優（+ 2010年）</item>
    <item>1918年 - 竹山逸郎、歌手（+ 1984年）</item>
    <item>1919年 - ドナルド・プレザンス、俳優（+ 1995年）</item>
    <item>1920年 - 藤村隆男、元プロ野球選手（+ 1993年）</item>
    <item>1923年 - 矢野徹、作家、翻訳家（+ 2004年）</item>
    <item>1924年 - ホセ・ドノソ、作家、ジャーナリスト（+ 1996年）</item>
    <item>1927年 - 舛田利雄、映画監督</item>
    <item>1928年 - アルベルト・スギ、画家（+ 2012年）</item>
    <item>1930年 - 豊島久真男、医学者</item>
    <item>1935年 - 堀内庄、元プロ野球選手（+ 2010年）</item>
    <item>1935年 - 柿本実、元プロ野球選手</item>
    <item>1936年 - 八田正、元プロ野球選手</item>
    <item>1936年 - アンネローゼ・シュミット、ピアニスト</item>
    <item>1936年 - ヴァーツラフ・ハヴェル、劇作家、政治家（+ 2011年）</item>
    <item>1941年 - 桂春蝶 (2代目)、落語家（+ 1993年）</item>
    <item>1943年 - 今野雄二、（映画・音楽）評論家、翻訳家（+ 2010年）</item>
    <item>1946年 - 西岡徳馬、俳優</item>
    <item>1947年 - 米田建三、政治家</item>
    <item>1947年 - ブライアン・ジョンソン、歌手（AC/DC）</item>
    <item>1949年 - やしきたかじん、歌手、タレント（+ 2014年）</item>
    <item>1949年 - 後藤謙次、キャスター</item>
    <item>1949年 - 照屋林賢、音楽家</item>
    <item>1950年 - 辺見マリ、歌手</item>
    <item>1951年 - ボブ・ゲルドフ、ミュージシャン（ブームタウン・ラッツ）、政治活動家</item>
    <item>1952年 - エモマリ・ラフモン、タジキスタン大統領</item>
    <item>1953年 - コジロー、漫画家</item>
    <item>1954年 - 原大輔、歌手</item>
    <item>1954年 - 李博士、ポンチャック歌手</item>
    <item>1955年 - 立野政治、元プロ野球選手</item>
    <item>1956年 - 郭源治、元プロ野球選手</item>
    <item>1956年 - 山口祐一郎、ミュージカル俳優</item>
    <item>1959年 - 渡邉美樹、ワタミ代表取締役社長</item>
    <item>1959年 - ロデリック・アレン、元プロ野球選手</item>
    <item>1960年 - カレカ、サッカー選手</item>
    <item>1960年 - 黒木瞳、元宝塚歌劇団月組主演娘役の女優</item>
    <item>1961年 - 内田利雄、騎手</item>
    <item>1961年 - 森本栄浩、毎日放送アナウンサー</item>
    <item>1961年 - クラウディア・クリストフィクス＝ビンダー、フィギュアスケート選手</item>
    <item>1962年 - マイケル・アンドレッティ、レーシングドライバー</item>
    <item>1963年 - 琴ヶ梅剛史、元力士、元大鳴戸親方</item>
    <item>1963年 - ローラ・デービース、プロゴルファー</item>
    <item>1964年 - 橋本聖子、スピードスケート選手・政治家</item>
    <item>1964年 - 太田あき、タレント</item>
    <item>1964年 - 横田めぐみ、北朝鮮による日本人拉致の被害者</item>
    <item>1964年 - 藤原啓治、声優</item>
    <item>1965年 - ディオニシオ・セロン、マラソン選手、ロンドンマラソンにおいて1995年-1997年まで3連覇をはたした</item>
    <item>1965年 - マリオ・ルミュー、元アイスホッケー選手、ソルトレイクシティオリンピック金メダリスト</item>
    <item>1965年 - パトリック・ロワ、元アイスホッケー選手、カナダ</item>
    <item>1966年 - イネッサ・クラベッツ、陸上競技選手、女子三段跳世界記録保持者、アトランタオリンピック女子三段跳金メダリスト</item>
    <item>1967年 - 森下由実子、歌手・元ソフトクリーム</item>
    <item>1967年 - ガイ・ピアース、俳優</item>
    <item>1970年 - 黒木永子、元グラビアアイドル</item>
    <item>1970年 - 宮崎吐夢、俳優</item>
    <item>1970年 - 浅井理恵、元AV女優、元ストリッパー</item>
    <item>1971年 - サムエル・ビンセント、声優</item>
    <item>1972年 - 酒井雄二、ミュージシャン（ゴスペラーズ）</item>
    <item>1972年 - 高橋コウタ、作曲家</item>
    <item>1972年 - グラント・ヒル、バスケットボール選手</item>
    <item>1972年 - アーロン・ガイエル、プロ野球選手</item>
    <item>1973年 - 永池恭男、元プロ野球選手</item>
    <item>1973年 - ルイス・ロペス、元プロ野球選手</item>
    <item>1973年 - 陳文賓、元プロ野球選手</item>
    <item>1974年 - 西島大介、漫画家・イラストレーター</item>
    <item>1974年 - リッチ・フランクリン、総合格闘家</item>
    <item>1975年 - ケイト・ウィンスレット、女優</item>
    <item>1975年 - Megumi、歌手（Paix2）</item>
    <item>1976年 - 刃田綴色、ドラマー</item>
    <item>1977年 - 木村一喜、プロ野球選手</item>
    <item>1977年 - コンスタンティン・ジリャノフ、サッカー選手</item>
    <item>1978年 - 山木陽介、記者</item>
    <item>1979年 - 石毛慎也、キックボクサー</item>
    <item>1979年 - 高圓圓、女優</item>
    <item>1980年 - 田臥勇太、バスケットボール選手</item>
    <item>1981年 - 筒井和也、プロ野球選手</item>
    <item>1981年 - うさみ恭香、元AV女優・元ストリッパー</item>
    <item>1981年 - 中東直己、プロ野球選手</item>
    <item>1981年 - ユリア・ラウトワ、フィギュアスケート選手</item>
    <item>1981年 - 張怡寧、卓球選手</item>
    <item>1982年 - 北野井子、元歌手・元タレント、ビートたけし〈北野武〉の長女</item>
    <item>1982年 - 米花剛史、ジャニーズJr.、Musical Academyのメンバー</item>
    <item>1982年 - 吉田沙保里、レスリング選手</item>
    <item>1982年 - ナタリー・ウランディス、フィギュアスケート選手</item>
    <item>1983年 - ニッキー・ヒルトン、ファッションモデル</item>
    <item>1983年 - 福徳秀介、お笑い芸人（ジャルジャル）</item>
    <item>1983年 - 川島慶三、プロ野球選手</item>
    <item>1983年 - ジェシー・アイゼンバーグ、俳優</item>
    <item>1983年 - アレクシー・オガンド、メジャーリーガー</item>
    <item>1983年 - フアン・マヌエル・バルガス、サッカー選手</item>
    <item>1983年 - 林祐征、サッカー選手</item>
    <item>1985年 - 三島輝史、プロ野球選手</item>
    <item>1985年 - ☆まかりな☆ - 双子お笑いコンビ（かな、まり）</item>
    <item>1987年 - 浜中文一、関西ジャニーズJr</item>
    <item>1987年 - かほり、歌手、294のメンバー</item>
    <item>1988年 - 糸谷哲郎、将棋棋士</item>
    <item>1988年 - 齋藤博樹、元騎手</item>
    <item>1988年 - 一ノ瀬優希、プロゴルファー</item>
    <item>1989年 - 梅井大輝、サッカー選手</item>
    <item>1989年 - 小野賢章、俳優・声優</item>
    <item>1989年 - 希美まゆ、AV女優</item>
    <item>1990年 - 栗原菊乃、タレント、堺正章の長女</item>
    <item>1990年 - 橘美緒、モデル</item>
    <item>1996年 - 重本ことり、Dream5のリーダー</item>
    <item>生年不明 - 斗羅、ドラマー（陰陽座）</item>
  </birthday>
  <anniversary>
    <item>578年 - ユスティヌス2世、東ローマ皇帝（* 520年）</item>
    <item>610年 - フォカス、東ローマ皇帝（* 547年?）</item>
    <item>785年（延暦4年8月28日） - 大伴家持、奈良時代の廷臣、歌人（* 718年頃）</item>
    <item>877年 - シャルル2世（禿頭王）、西フランク王（* 823年）</item>
    <item>1056年 - ハインリヒ3世、ドイツ王、神聖ローマ皇帝（* 1017年）</item>
    <item>1111年 - ロベール2世、フランドル伯（* 1065年頃）</item>
    <item>1237年（嘉禎3年9月15日） - 正親町三条公氏、鎌倉時代の公卿（* 1182年）</item>
    <item>1285年 - フィリップ3世、フランス王（* 1245年）</item>
    <item>1524年 - ヨアヒム・パティニール、画家（* 1480年頃）</item>
    <item>1565年 - ルドヴィコ・フェラーリ、数学者（* 1522年）</item>
    <item>1638年（寛永15年8月28日） - 荒木又右衛門、剣客（* 1599年）</item>
    <item>1650年（慶安3年9月10日） - 松平忠直、第2代越前藩主（* 1597年）</item>
    <item>1714年（正徳4年8月27日） - 貝原益軒、儒学者（* 1630年）</item>
    <item>1763年 - アウグスト3世、ポーランド王（* 1696年）</item>
    <item>1805年 - チャールズ・コーンウォリス、イギリス軍の将軍、インド総督（* 1738年）</item>
    <item>1813年 - テカムセ、アメリカ先住民ショーニー族の首長（* 1768年?）</item>
    <item>1816年（文化13年閏8月14日） - 塩原太助、江戸時代の豪商（* 1743年）</item>
    <item>1837年 - オルタンス・ド・ボアルネ、ホラント王ルイ・ボナパルトの妃（* 1783年）</item>
    <item>1853年 - マーロン・ディカーソン、アメリカ合衆国海軍長官（* 1770年）</item>
    <item>1864年（元治元年9月5日）- 清岡道之助、尊王攘夷の活動家（* 1833年）</item>
    <item>1866年 - レオポルト・フォン・ヘニング、哲学者（* 1791年）</item>
    <item>1871年（明治4年8月21日） - 九条尚忠、江戸時代の公卿（* 1798年）</item>
    <item>1880年 - ウィリアム・ラッセル、天文学者（* 1799年）</item>
    <item>1880年 - ジャック・オッフェンバック、作曲家（* 1819年）</item>
    <item>1899年 - ジェイムズ・ハーラン、第8代アメリカ合衆国内務長官（* 1820年）</item>
    <item>1912年 - ルイス・ボス、天文学者（* 1846年）</item>
    <item>1912年 - 穂積八束、法学者（* 1860年）</item>
    <item>1918年 - ローラン・ギャロス、フランス軍のエース・パイロット（* 1888年）</item>
    <item>1920年 - 末松謙澄、ジャーナリスト、政治家（* 1855年）</item>
    <item>1934年 - ジャン・ヴィゴ、映画監督（* 1905年）</item>
    <item>1938年 - 高村智恵子、洋画家、高村光太郎の妻（* 1886年）</item>
    <item>1940年 - シルベストレ・レブエルタス、作曲家、指揮者、ヴァイオリニスト（* 1899年）</item>
    <item>1944年 - 頭山満、国家主義運動家（* 1855年）</item>
    <item>1948年 - ゲオルク・クーレンカンプ、ヴァイオリニスト（+ 1898年）</item>
    <item>1948年 - 大谷光瑞、宗教家・冒険家、浄土真宗本願寺派第22世法主（* 1876年）</item>
    <item>1951年 - 小平浪平、実業家、日立製作所創業者（* 1874年）</item>
    <item>1955年 - 河合小市、実業家、河合楽器創業者（* 1886年）</item>
    <item>1960年 - アルフレッド・L・クローバー、文化人類学者（* 1876年）</item>
    <item>1972年 - ソロモン・レフシェッツ、数学者（* 1884年）</item>
    <item>1974年 - ザルマン・シャザール、作家、イスラエル大統領（* 1889年）</item>
    <item>1976年 - ラルス・オンサーガー、物理学者（* 1903年）</item>
    <item>1976年 - 武田泰淳、小説家（* 1912年）</item>
    <item>1977年 - 和田芳恵、小説家（* 1906年）</item>
    <item>1980年 - 四代目三遊亭小圓遊、落語家（*1937年）</item>
    <item>1981年 - グロリア・グレアム、女優（* 1923年）</item>
    <item>1982年 - 小畑勇二郎、秋田県知事（* 1906年）</item>
    <item>1985年 - カール・メンガー、数学者（* 1902年）</item>
    <item>1986年 - ジェームズ・H・ウィルキンソン、数学者（* 1919年）</item>
    <item>1989年 - 佐伯勇、実業家（* 1903年）</item>
    <item>1990年 - 岡義武、政治学者（* 1902年）</item>
    <item>1994年 - 中条静夫、俳優（* 1926年）</item>
    <item>1994年 - ニニ・ロッソ、ジャズトランペット奏者（* 1927年）</item>
    <item>1995年 - アレック・ダグラス＝ヒューム、イギリス首相（* 1903年）</item>
    <item>1995年 - 島田一男、社会心理学者、評論家（* 1923年）</item>
    <item>1996年 - シーモア・クレイ、スーパーコンピュータ設計者（* 1925年）</item>
    <item>1996年 - 野口明、元プロ野球選手（* 1917年）</item>
    <item>2000年 - 永倉万治、作家（* 1948年）</item>
    <item>2001年 - マイケル・マンスフィールド、在日本アメリカ合衆国大使（* 1903年）</item>
    <item>2001年 - 瀬長亀次郎、沖縄人民党書記長、那覇市長、日本共産党副委員長（* 1907年）</item>
    <item>2001年 - セーケイ・ゾルターン、ヴァイオリニスト、作曲家（* 1903年）</item>
    <item>2002年 - 三鬼陽之助、経済評論家（* 1907年）</item>
    <item>2003年 - ティモシー・トレッドウェル (Timothy Treadwell)、グリズリー研究家（* 1957年）</item>
    <item>2004年 - モーリス・ウィルキンス、生物物理学者（* 1916年）</item>
    <item>2007年 - 村松定孝、国文学者（* 1918年）</item>
    <item>2007年 - 星川薫、元調教師（* 1930年）</item>
    <item>2008年 - 土屋義彦、政治家、元埼玉県知事（* 1926年）</item>
    <item>2008年 - 緒形拳、俳優（* 1937年）</item>
    <item>2008年 - 福田和禾子、作曲家（* 1941年）</item>
    <item>2011年 - スティーブ・ジョブズ、アップル共同創業者・同社前CEO（* 1955年）</item>
    <item>2013年 - 桜塚やっくん、男性お笑いタレント、声優、俳優（* 1976年）</item>
    <item>2014年 - 大山勝美、演出家（* 1932年）</item>
    <item>2014年 - アンドレア・デ・チェザリス、レーシングドライバー（* 1959年）</item>
  </anniversary>
  <topic>
    <item>国際連合教育科学文化機関（ユネスコ）が制定した国際デー。1966年のこの日、「教師の地位向上に関する勧告」が調印されたことにちなむ。</item>
    <item>共和制樹立記念日</item>
    <item>1910年10月5日革命により国王マヌエル2世が退位し、王政から共和制へ移行したことを記念。</item>
    <item>憲法記念日</item>
    <item>レジ袋ゼロデー</item>
    <item>日本チェーンストア協会が2002年に、ゴミ減量のために買物袋（マイバッグ）の持参を呼びかけるために制定。</item>
    <item>時刻表記念日</item>
    <item>1894年10月5日に、日本で初めての本格的な時刻表『汽車汽船旅行案内』が庚寅新誌社から出版されたことに由来。これは福沢諭吉の勧めにより手塚猛昌が発行したもので、列車の発車時刻や運賃のほか、沿線の案内や紀行文なども掲載されていた。</item>
    <item>レモンの日</item>
    <item>1938年のこの日に詩人の高村光太郎の妻・智恵子が亡くなり、亡くなる数時間前にレモンをかじる姿をうたった、「そんなにもあなたはレモンを待っていた・・・私の手からとつた一つのレモンをあなたのきれいな歯ががりりと噛んだ」という「智恵子抄」の「レモン哀歌」にちなんでいる。</item>
    <item>The most populous birthday of the year statistically in U.S.</item>
    <item>アメリカで、1年でもっとも多くの人が誕生日を迎える日。統計によれば毎年平均12,576人の人がこの日に生まれる。そして、毎年およそ968,000人のアメリカ人が誕生日を迎えるという。</item>
    <item>関連リンク：http://anybirthday.com/report.htm Anybirthday.com</item>
  </topic>
</items>
