<?xml version="1.0" encoding="UTF-8" standalone="yes"?>
<items>
  <description>
    <item>10月4日（じゅうがつよっか）はグレゴリオ暦で年始から277日目（閏年では278日目）にあたり、年末まであと88日ある。</item>
  </description>
  <events>
    <item>663年（天智天皇2年8月27日） - 白村江の戦いが始まる。</item>
    <item>1363年（至正23年/大定3年8月26日） - 鄱陽湖の戦いが終結。朱元璋が陳友諒を破る。</item>
    <item>1582年 - イタリア・ポーランド・ポルトガル・スペインでグレゴリオ暦の適用により、10月4日の翌日が10月15日になる。</item>
    <item>1636年 - 三十年戦争・フランス・スウェーデン戦争: ヴィットストックの戦い。</item>
    <item>1745年 - フランツ1世が神聖ローマ帝国皇帝に即位。</item>
    <item>1777年 - アメリカ独立戦争: ジャーマンタウンの戦い</item>
    <item>1808年（文化5年8月15日） - イギリス軍艦が長崎港に侵入、オランダ商館員を人質に食料などを要求。（フェートン号事件）</item>
    <item>1824年 - メキシコが新憲法を制定し共和制に移行。</item>
    <item>1830年 - ベルギーがオランダからの独立を宣言。</item>
    <item>1853年 - クリミア戦争: オスマン帝国がロシアに宣戦布告。</item>
    <item>1868年（明治元年8月19日） - 榎本武揚率いる旧江戸幕府艦隊が江戸を脱出する。</item>
    <item>1883年 - オリエント急行が運行開始。</item>
    <item>1895年 - 第1回全米オープンゴルフ開催。</item>
    <item>1910年 - ポルトガルの革命で王族がイギリスへ亡命。</item>
    <item>1927年 - ガットスン・ボーグラムがラシュモア山の大統領像の彫刻を開始。</item>
    <item>1945年 - GHQが「民権自由に関する指令（政治的、公民的及び宗教的自由に対する制限の除去の覚書）」を発令し、人権の確立・治安維持法の撤廃・政治犯の釈放を指示。</item>
    <item>1945年 - 特別高等警察廃止。</item>
    <item>1951年 - 出入国管理令（現在の出入国管理及び難民認定法）公布。</item>
    <item>1954年 - 日本テレビ系ニュース番組『NNNきょうの出来事』が放送開始。</item>
    <item>1957年 - ソビエト連邦が世界初の人工衛星であるスプートニク1号を打ち上げ。</item>
    <item>1958年 - フランスで新憲法が発効し、フランス第五共和政が開始。</item>
    <item>1965年 - ローマ教皇パウロ6世が、歴代教皇では史上初めてアメリカ合衆国を訪問。</item>
    <item>1966年 - レソトがイギリスから独立。</item>
    <item>1967年 - ハサナル・ボルキアがブルネイ国王に即位。</item>
    <item>1969年 - TBS系バラエティ番組『8時だョ!全員集合』が放送開始。（ - 1985年9月）</item>
    <item>1970年 - 日本テレビ系旅番組『遠くへ行きたい』（読売テレビ制作）が放送開始（現在も放送中）。</item>
    <item>1978年 - 内閣府に原子力安全委員会設置。</item>
    <item>1978年 - エルサルバドルで誘拐されていた合弁企業インシンカ社（INSINCA）社長・松本不二雄が死体で発見される。</item>
    <item>1982年 - フジテレビ系生放送バラエティ番組『森田一義アワー 笑っていいとも!』が放送開始（～2014年3月31日終了）。</item>
    <item>1985年 - リチャード・ストールマンがフリーソフトウェア財団を設立。</item>
    <item>1988年 - ベトナム・ホーチミン市で二重体児・ベトちゃん・ドクちゃんの分離手術。</item>
    <item>1991年 - 第11回南極条約特別協議国会議でが採択される。</item>
    <item>1992年 - エル・アル航空1862便墜落事故。</item>
    <item>1993年 - 10月政変: 反エリツィン派が立てこもるモスクワのロシア最高会議ビルを戦車で砲撃、議会側は降伏する。</item>
    <item>1994年 - 北海道東方沖地震</item>
    <item>2001年 - シベリア航空機撃墜事件。シベリア航空機がウクライナ防空軍のミサイルの誤射により墜落。78人全員死亡。</item>
    <item>2003年 - イスラエル・ハイファのレストランで自爆テロ、21人が死亡。(:Maxim restaurant suicide bombing)</item>
    <item>2004年 - 有人宇宙船スペースシップワンが宇宙船開発賞金Ansari X Prizeの基準を達成。</item>
    <item>2005年 - ハリケーン・スタンがメキシコ南部ベラクルス州に上陸。グアテマラを中心に死者千人以上。</item>
    <item>2014年 -JR東日本南武線にE233系電車が運用を開始する。</item>
  </events>
  <birthday>
    <item>1289年 - ルイ10世、フランス王（+ 1316年）</item>
    <item>1472年 - ルーカス・クラナッハ、画家（+ 1553年）</item>
    <item>1515年 - ルーカス・クラナッハ（子）、画家（+ 1586年）</item>
    <item>1615年 - フィリップ・ヴィルヘルム、プファルツ＝ノイブルク公（+ 1690年）</item>
    <item>1626年 - リチャード・クロムウェル、イギリスの第2代護国卿（+ 1712年）</item>
    <item>1665年（寛文5年8月26日） - 徳川綱教、第3代和歌山藩主、徳川吉宗の兄（+ 1705年）</item>
    <item>1720年 - ジョヴァンニ・バッティスタ・ピラネージ、画家、建築家（+ 1778年）</item>
    <item>1787年 - フランソワ・ピエール・ギヨーム・ギゾー、フランスの政治家（+ 1874年）</item>
    <item>1791年 - レオポルト・フォン・ヘニング、哲学者（+ 1866年）</item>
    <item>1814年 - ジャン＝フランソワ・ミレー、画家（+ 1875年）</item>
    <item>1822年 - ラザフォード・ヘイズ、第19代アメリカ合衆国大統領（+ 1893年）</item>
    <item>1870年（明治3年9月10日） - 木村栄、天文学者（+ 1943年）</item>
    <item>1876年 - 新村出、広辞苑の編纂者として知られる言語学者（+ 1967年）</item>
    <item>1877年 - 伊良子清白、詩人（+ 1946年）</item>
    <item>1878年 - アーサー・ホプキンス、劇作家、脚本家、映像監督、プロデューサー（+ 1950年）</item>
    <item>1884年 - 辻潤、翻訳家、思想家（+ 1944年）</item>
    <item>1888年 - 中原悌二郎、彫刻家（+ 1921年）</item>
    <item>1895年 - バスター・キートン、喜劇俳優（+ 1966年）</item>
    <item>1895年 - リヒャルト・ゾルゲ、ドイツの共産主義者（+ 1944年）</item>
    <item>1898年 - 増田甲子七、政治家（+ 1985年）</item>
    <item>1902年 - 河盛好蔵、フランス文学者・評論家（+ 2000年）</item>
    <item>1908年 - 森喜作、農学者、実業家（+ 1977年）</item>
    <item>1911年 - 日野原重明、医師</item>
    <item>1914年 - エディ・タウンゼント、ボクシングトレーナー（+ 1988年）</item>
    <item>1918年 - 福井謙一、化学者（+ 1998年）</item>
    <item>1922年 - 重光武雄、実業家</item>
    <item>1922年 - 武末悉昌、元プロ野球選手（＋ 1998年）</item>
    <item>1924年 - チャールトン・ヘストン、俳優（+ 2008年）</item>
    <item>1925年 - 山口鶴男、政治家</item>
    <item>1926年 - 西島和彦、物理学者（+ 2009年）</item>
    <item>1927年 - エバ・パブリック、フィギュアスケート選手（+ 1983年）</item>
    <item>1928年 - 三木申三、政治家（+ 2010年）</item>
    <item>1928年 - アルビン・トフラー、評論家、作家、未来学者</item>
    <item>1935年 - 近藤高子、声優</item>
    <item>1936年 - 北島三郎、歌手</item>
    <item>1941年 - アン・ライス、小説家</item>
    <item>1943年 - 河野義博、元スピードスケート選手</item>
    <item>1944年 - 黒田アキ、芸術家</item>
    <item>1944年 - トニー・ラルーサ、メジャーリーグ監督</item>
    <item>1948年 - 上杉純雄、みちのく銀行会長、ユーシーカード元社長</item>
    <item>1959年 - 辻仁成、小説家、ミュージシャン</item>
    <item>1959年 - クリス・ロウ、ミュージシャン（ペット・ショップ・ボーイズ）</item>
    <item>1959年 - 鵜飼菜穂子、競艇選手</item>
    <item>1960年 - 松山尚子、女優</item>
    <item>1960年 - 土屋公平、ミュージシャン</item>
    <item>1961年 - 浅野妙子、脚本家</item>
    <item>1963年 - 高橋和希、漫画家</item>
    <item>1963年 - いしかわこうじ、絵本作家、イラストレーター</item>
    <item>1964年 - 柿崎澄子、女優</item>
    <item>1964年 - マーク・マクレモア、元メジャーリーグ選手（内野手、外野手）</item>
    <item>1965年 - 金谷ヒデユキ、元お笑い芸人</item>
    <item>1965年 - 根谷美智子、声優</item>
    <item>1967年 - 小山剛志、俳優、声優</item>
    <item>1967年 - イーキン・チェン、香港の俳優、歌手</item>
    <item>1967年 - 阿部恵、アナウンサー</item>
    <item>1968年 - 野村誠、作曲家</item>
    <item>1971年 - 仁志敏久、プロ野球選手</item>
    <item>1971年 - 桶田敬太郎、元フォークダンスDE成子坂</item>
    <item>1971年 - 千聖、ミュージシャン（PENICILLIN）</item>
    <item>1971年 - 藤田俊哉、サッカー選手</item>
    <item>1971年 - カレン・トン、香港の歌手・女優</item>
    <item>1971年 - 今石洋之、アニメーター、アニメーション監督</item>
    <item>1972年 - アダム・リグス、プロ野球選手</item>
    <item>1972年 - 高橋英樹、元プロ野球選手</item>
    <item>1973年 - 吉原由香里（旧姓梅沢）、女流棋士</item>
    <item>1974年 - 笹島かほる、声優</item>
    <item>1974年 - 高野直子、元朝日放送アナウンサー</item>
    <item>1976年 - 清水範久、サッカー選手</item>
    <item>1976年 - 森笠繁、プロ野球選手</item>
    <item>1976年 - さくらえみ、プロレスラー</item>
    <item>1976年 - 小川信行、俳優</item>
    <item>1976年 - アリシア・シルヴァーストーン、アメリカ出身の女優</item>
    <item>1977年 - 藤本敦士、プロ野球選手</item>
    <item>1977年 - 前田忠節、プロ野球選手</item>
    <item>1978年 - ペース・ウー、台湾のタレント</item>
    <item>1978年 - 吉崎勝、プロ野球選手</item>
    <item>1978年 - 高倉啓司、野球選手</item>
    <item>1978年 - 平井英一、野球選手</item>
    <item>1978年 - 相沢まみ、AV女優</item>
    <item>1979年 - 香川みどり、歌手</item>
    <item>1979年 - レイチェル・リー・クック、女優</item>
    <item>1980年 - 高城元気、声優</item>
    <item>1980年 - 原万紀子、タレント</item>
    <item>1980年 - トマーシュ・ロシツキー、サッカー選手</item>
    <item>1981年 - 平中克幸、レーシングドライバー</item>
    <item>1982年 - mie、ファッションモデル</item>
    <item>1982年 - 那須野巧、プロ野球選手</item>
    <item>1982年 - 近木裕哉、声優</item>
    <item>1983年 - 上田竜也、KAT-TUN</item>
    <item>1983年 - 工藤里紗、グラビアアイドル</item>
    <item>1983年 - 前田愛、女優</item>
    <item>1983年 - セルゲイ・アントノフ、チェリスト</item>
    <item>1984年 - リェーナ・カーチナ、T.A.T.u.メンバー</item>
    <item>1984年 - 松原大典、声優</item>
    <item>1984年 - 八田亜矢子、タレント</item>
    <item>1984年 - ドリュー・スタッブス、メジャーリーガー</item>
    <item>1985年 - 張丹、フィギュアスケート選手</item>
    <item>1986年 - エリエル・サンチェス、野球選手</item>
    <item>1987年 - 佐々木喜英、俳優</item>
    <item>1987年 - 村川絵梨、女優・歌手</item>
    <item>1987年 - 榎園実穂、女優</item>
    <item>1987年 - 田中亜土夢、サッカー選手</item>
    <item>1988年 - 森絵梨佳、モデル、グラビアアイドル</item>
    <item>1988年 - ロニー・チゼンホール、メジャーリーガー</item>
    <item>1989年 - キミー・マイズナー、フィギュアスケート選手</item>
    <item>1990年 - 河合優、女優、アイドル</item>
    <item>1990年 - 土屋健二、プロ野球選手</item>
    <item>1990年 - キャメロン・ヒムズ、フィギュアスケート選手</item>
    <item>1992年 - 渡辺泰広、サッカー選手</item>
    <item>1994年 - 土田真里恵、女優</item>
    <item>生年不明 - 木村真一郎、アニメーション監督</item>
    <item>生年不明 ｰ   長瀬館長   ,プロレスラー</item>
  </birthday>
  <anniversary>
    <item>1305年（嘉元3年9月15日） - 亀山天皇、日本の第90代天皇（* 1249年）</item>
    <item>1582年 - アビラのテレサ、カトリック教会の神秘家（* 1515年）</item>
    <item>1669年 - レンブラント・ファン・レイン、画家（* 1606年）</item>
    <item>1718年（享保3年9月11日） - 徳川綱條、常陸国水戸藩の第3代藩主（* 1656年）</item>
    <item>1880年 - ジャック・オッフェンバック、作曲家（* 1819年）</item>
    <item>1903年 - オットー・ヴァイニンガー、哲学者（* 1880年）</item>
    <item>1904年 - フレデリク・バルトルディ、自由の女神像の製作者である彫刻家・建築家（* 1834年）</item>
    <item>1947年 - マックス・プランク、物理学者（* 1858年）</item>
    <item>1970年 - ジャニス・ジョプリン、歌手（* 1943年）</item>
    <item>1972年 - 東海林太郎、歌手（* 1898年）</item>
    <item>1975年 - メイ・サットン、テニス選手（* 1886年）</item>
    <item>1976年 - 高野素十、俳人、医学博士（* 1893年）</item>
    <item>1980年 - ソラーシュ・ラースロー、フィギュアスケート選手（* 1907年）</item>
    <item>1981年 - 保田與重郎、文芸評論家（* 1910年）</item>
    <item>1982年 - グレン・グールド、ピアニスト（* 1932年）</item>
    <item>1984年 - カール・フォン・ガラグリ、ヴァイオリニスト、指揮者（* 1900年）</item>
    <item>1989年 - グレアム・チャップマン、コメディアン（モンティ・パイソン）（* 1941年）</item>
    <item>1992年 - デニス・ハルム、F1レーサー（* 1936年）</item>
    <item>1996年 - シルヴィオ・ピオラ、サッカー選手（* 1913年）</item>
    <item>1996年 - 小林正樹、映画監督（* 1916年）</item>
    <item>1997年 - 横井軍平、ゲームクリエーター（* 1941年）</item>
    <item>1999年 - アート・ファーマー、ジャズトランペット奏者（* 1928年）</item>
    <item>1999年 - ベルナール・ビュフェ、画家（* 1928年）</item>
    <item>2002年 - ペーター・リバール、ヴァイオリニスト（* 1913年）</item>
    <item>2002年 - 平凡太郎、俳優、コメディアン（* 1933年）</item>
    <item>2004年 - ゴードン・クーパー、宇宙飛行士（* 1927年）</item>
    <item>2009年 - 浅井美幸、公明党副委員長（* 1927年）</item>
    <item>2009年 - メルセデス・ソーサ、フォルクローレ歌手（* 1935年）</item>
    <item>2009年 - 原口幸市、日本の外交官（* 1940年）</item>
    <item>2013年 - ヴォー・グエン・ザップ、ベトナムの軍人･政治家（* 1911年）</item>
    <item>2013年 - 三善晃、作曲家（* 1933年）</item>
    <item>1989年 - セクレタリアト、競走馬（* 1970年）</item>
    <item>2011年 - シンボリルドルフ、競走馬（* 1981年）</item>
  </anniversary>
  <topic>
    <item>世界動物の日</item>
    <item>動物・環境保護の守護聖人であるアッシジのフランチェスコの聖名祝日。</item>
    <item>（ - 10月10日）</item>
    <item>1999年12月の国連総会で制定された国際週間。1957年に世界初の人工衛星・スプートニク1号が打ち上げられた10月4日から、1967年に宇宙条約が発効した10月10日までの1週間。</item>
    <item>独立記念日</item>
    <item>1966年のこの日、レソトがイギリスから独立した。</item>
    <item>都市景観の日</item>
    <item>「と(10)し(4)び」（都市美）の語呂合せ。建設省等が1990年に制定。</item>
    <item>里親デー</item>
    <item>厚生省が1950年に制定。1948年のこの日、里親制度の運営についての厚生事務次官通告が施行されたことを記念。</item>
    <item>証券投資の日</item>
    <item>「とう(10)し(4)」（投資）の語呂合せ。日本証券業協会が1996年に制定。</item>
    <item>古書の日</item>
    <item>全国古書籍商組合連合会が2003年に制定。「古」の字を分解して「十」「口」とし、これを組あわせた「田」を4冊の本に見立てて10月4日を記念日とした。</item>
    <item>イワシの日</item>
    <item>「い(1)わ(0)し(4)」の語呂合せ。多獲性魚有効利用検討会（現 大阪おさかな健康食品協議会）が1985年に制定。</item>
    <item>陶器の日</item>
    <item>日本陶磁器卸商業協同組合連合会が1984年に制定。陶器の古称「陶瓷（とうし）」から、「とう(10)し(4)」の語呂合せ。</item>
    <item>天使の日</item>
    <item>「てん(10)し(4)」の語呂合わせ。トリンプインターナショナルジャパンが制定。</item>
    <item>徒歩の日</item>
    <item>日常生活で歩く習慣を取り戻し健康になろうと宮崎市の徒歩を楽しむ会代表が制定。日付は10と4で「トウフォー」と読む語呂合わせから</item>
  </topic>
</items>
